binance_bigdata/__init__.py
binance_bigdata/__main__.py
binance_bigdata-0.1.0.dist-info/WHEEL
binance_bigdata-0.1.0.dist-info/METADATA
binance_bigdata-0.1.0.dist-info/RECORD
